docker_migration/__init__.py
docker_migration/main.py
docker_migration/archive/__init__.py
docker_migration/archive/archiver.py
docker_migration/archive/extractor.py
docker_migration/docker_utils/__init__.py
docker_migration/docker_utils/compose_parser.py
docker_migration/docker_utils/docker_backup.py
docker_migration/transfer/__init__.py
docker_migration/transfer/file_transfer.py
docker_migration/validation/__init__.py
docker_migration/validation/health_check.py
docker_migration-0.2.0.dist-info/licenses/LICENSE
docker_migration-0.2.0.dist-info/METADATA
docker_migration-0.2.0.dist-info/WHEEL
docker_migration-0.2.0.dist-info/entry_points.txt
docker_migration-0.2.0.dist-info/top_level.txt
docker_migration-0.2.0.dist-info/RECORD
