Metadata-Version: 2.4
Name: docker-migration
Version: 0.2.0
Summary: A tool for migrating Docker applications between servers
Home-page: https://github.com/HMCorp-Fund/docker_migration
Author: Anton Pavlenko
Author-email: apavlenko@hmcorp.fund
Requires-Python: >=3.6
License-File: LICENSE
Requires-Dist: docker
Requires-Dist: requests
Requires-Dist: paramiko
Requires-Dist: pyyaml
Requires-Dist: zipfile36
Requires-Dist: humanize
Dynamic: author
Dynamic: author-email
Dynamic: description
Dynamic: description-content-type
Dynamic: home-page
Dynamic: license-file
Dynamic: requires-dist
Dynamic: requires-python
Dynamic: summary
